Workbook

Sheet Dashboard
A1: Carly's Clippers — Spreadsheet Analysis Dashboard
A2: Google Sheets compatible · All key metrics use live formulas · Yellow cells are editable inputs (see Simulator sheet)
A4: RECOMMENDATION FOR CARLY | F4: KEY METRICS AT A GLANCE
A5: Advertise the four styles under $30 after the $5 discount (bouffant, pixie, crew, bowl). Protect the high-margin mohawk ($300 last week). Monitor crew volume (most popular). Test a smaller discount ($3) first — a flat $5 cut costs ~$680 over 4 weeks if volume is unchanged. | F5: Metric | G5: Value
F6: Average Price (original) | G6: ='Source Data'!B12 -> 31.875
F7: Total Revenue (last week) | G7: ='Source Data'!D12 -> 1085
F8: Avg Daily Revenue | G8: ='Source Data'!D13 -> 155
F9: Styles under $30 (new prices) | G9: ='Source Data'!F12 -> 4
A10: CUTS CURRENTLY UNDER $30 (default $5 discount) | F10: Most popular style | G10: ='Source Data'!B14 -> crew
A11: These four styles are under $30 at the default discount. Change Discount on Simulator → check Source Data “Under $30?” column for the live list. | F11: Highest-revenue style | G11: ='Source Data'!B15 -> mohawk
F12: Total haircuts last week | G12: ='Source Data'!C12 -> 34
A13: Style | B13: New Price | C13: Units Sold | D13: Rev @ New Price
A14: ='Source Data'!A4 -> bouffant | B14: ='Source Data'!E4 -> 25 | C14: ='Source Data'!C4 -> 2 | D14: ='Source Data'!E4*'Source Data'!C4 -> 50
A15: ='Source Data'!A5 -> pixie | B15: ='Source Data'!E5 -> 20 | C15: ='Source Data'!C5 -> 3 | D15: ='Source Data'!E5*'Source Data'!C5 -> 60
A16: ='Source Data'!A7 -> crew | B16: ='Source Data'!E7 -> 15 | C16: ='Source Data'!C7 -> 8 | D16: ='Source Data'!E7*'Source Data'!C7 -> 120
A17: ='Source Data'!A8 -> bowl | B17: ='Source Data'!E8 -> 15 | C17: ='Source Data'!C8 -> 4 | D17: ='Source Data'!E8*'Source Data'!C8 -> 60
A19: HOW TO USE THIS WORKBOOK
A20: 1. Go to Simulator sheet → change the yellow Discount ($) or Sales Multiplier cells. 2. Source Data and Dashboard recalculate automatically via formulas. 3. Charts Data feeds the embedded charts; they refresh when values change. 4. Upload to Google Sheets: File → Import → Upload → Replace spreadsheet. Yellow input cells stay editable.

Sheet Source Data
A1: Source Data — Hairstyles, Prices & Last Week Sales
A2: Blue text + yellow background = editable inputs. Black/green formulas recalculate everything. Discount is controlled on Simulator!B3.
A3: Style | B3: Original Price ($) | C3: Units Last Week | D3: Revenue ($) | E3: New Price ($) | F3: Under $30? | G3: Revenue @ New Price ($)
A4: bouffant | B4: 30 | C4: 2 | D4: =B4*C4 -> 60 | E4: =B4-Simulator!$B$3 -> 25 | F4: =IF(E4<30,"Yes","No") -> Yes | G4: =E4*C4 -> 50
A5: pixie | B5: 25 | C5: 3 | D5: =B5*C5 -> 75 | E5: =B5-Simulator!$B$3 -> 20 | F5: =IF(E5<30,"Yes","No") -> Yes | G5: =E5*C5 -> 60
A6: dreadlocks | B6: 40 | C6: 5 | D6: =B6*C6 -> 200 | E6: =B6-Simulator!$B$3 -> 35 | F6: =IF(E6<30,"Yes","No") -> No | G6: =E6*C6 -> 175
A7: crew | B7: 20 | C7: 8 | D7: =B7*C7 -> 160 | E7: =B7-Simulator!$B$3 -> 15 | F7: =IF(E7<30,"Yes","No") -> Yes | G7: =E7*C7 -> 120
A8: bowl | B8: 20 | C8: 4 | D8: =B8*C8 -> 80 | E8: =B8-Simulator!$B$3 -> 15 | F8: =IF(E8<30,"Yes","No") -> Yes | G8: =E8*C8 -> 60
A9: bob | B9: 35 | C9: 4 | D9: =B9*C9 -> 140 | E9: =B9-Simulator!$B$3 -> 30 | F9: =IF(E9<30,"Yes","No") -> No | G9: =E9*C9 -> 120
A10: mohawk | B10: 50 | C10: 6 | D10: =B10*C10 -> 300 | E10: =B10-Simulator!$B$3 -> 45 | F10: =IF(E10<30,"Yes","No") -> No | G10: =E10*C10 -> 270
A11: flattop | B11: 35 | C11: 2 | D11: =B11*C11 -> 70 | E11: =B11-Simulator!$B$3 -> 30 | F11: =IF(E11<30,"Yes","No") -> No | G11: =E11*C11 -> 60
A12: TOTAL / AVERAGE | B12: =AVERAGE(B4:B11) -> 31.875 | C12: =SUM(C4:C11) -> 34 | D12: =SUM(D4:D11) -> 1085 | E12: =AVERAGE(E4:E11) -> 26.875 | F12: =COUNTIF(F4:F11,"Yes") -> 4 | G12: =SUM(G4:G11) -> 915
A13: Avg Daily Revenue (Total Rev / 7) | D13: =D12/7 -> 155
A14: Most popular style | B14: =INDEX(A4:A11,MATCH(MAX(C4:C11),C4:C11,0)) -> crew | C14: =MAX(C4:C11) -> 8
A15: Highest-revenue style | B15: =INDEX(A4:A11,MATCH(MAX(D4:D11),D4:D11,0)) -> mohawk | C15: =MAX(D4:D11) -> 300
A17: Edit yellow cells (price or units) or change Discount on Simulator. All formulas + Dashboard update automatically. This is the spreadsheet equivalent of the Python lists + loops + list comprehensions.

Sheet Calculations
A1: Step-by-Step Calculations (Spreadsheet equivalents of the Python notebook tasks)
A2: Each block shows the classic approach and the compact formula. Values are live and linked to Source Data / Simulator.
A4: 1. AVERAGE HAIRCUT PRICE
A5: total_price (SUM of prices) | B5: =SUM('Source Data'!B4:B11) -> 255 | C5: ← =SUM(...) equivalent to the for-loop that adds each price
A6: average_price | B6: =B5/COUNTA('Source Data'!A4:A11) -> 31.875 | C6: ← total_price / number of styles (len(prices) in Python)
A7: Notebook-style print | B7: =CONCATENATE("Average Haircut Price: ", TEXT(B6,"0.000")) -> Average Haircut Price: 31.875 | C7: Matches the required print format from the original project
A9: 2. NEW PRICES (all reduced by Discount)
A10: Discount amount (live from Simulator) | B10: =Simulator!B3 -> 5 | C10: Change this on the Simulator sheet (yellow cell B3)
A11: new_prices live in Source Data column E | C11: Each cell: =OriginalPrice − Discount (list-comprehension equivalent)
A13: 3. TOTAL REVENUE LAST WEEK
A14: total_revenue | B14: ='Source Data'!D12 -> 1085 | C14: ← SUM of (price × units) for each style (indexed for-loop equivalent)
A15: Notebook-style print | B15: =CONCATENATE("Total Revenue: ", TEXT(B14,"0")) -> Total Revenue: 1085
A17: 4. AVERAGE DAILY REVENUE
A18: average_daily_revenue | B18: =B14/7 -> 155 | C18: total_revenue / 7
A20: 5. CUTS UNDER $30 AFTER DISCOUNT
A21: Count of styles with New Price < 30 | B21: ='Source Data'!F12 -> 4 | C21: COUNTIF on the Under $30? column (filter / list-comp equivalent)
A22: Full list is on the Source Data sheet. Apply a filter (Data → Create a filter) on the Under $30? column to see only the Yes rows.
A24: WHAT SPREADSHEETS SHOW ESPECIALLY WELL
A25: • Instant recalculation when any price or unit count changes (no need to re-run a script). • Conditional formatting that paints “Yes/No” and low prices automatically. • What-if analysis is just editing one yellow cell (Simulator). • Charts stay linked to the data ranges and update live. • Easy to share with non-coders — Carly can open this in Google Sheets on her phone. • INDEX/MATCH and SUMPRODUCT replace many of the manual loops used in the Python version.

Sheet Simulator
A1: What-If Simulator — Change Inputs, Watch Metrics Update
A2: Yellow cells with blue text are the only inputs you need to edit. Everything else is formula-driven and updates across the whole workbook.
A3: Discount amount ($) | B3: 5 | C3: ← Change this (try 3, 5, 8, 10). New prices & Under-$30 flags update everywhere.
A4: Sales multiplier | B4: 1 | C4: ← 1.0 = last week as-is; 1.5 = 50% busier; 0.7 = slower week. Scales projected revenue.
A6: SIMULATED RESULTS (current Source Data prices × multiplier + Discount above)
A7: Simulated total units | B7: =ROUND('Source Data'!C12*B4,0) -> 34 | C7: Original total units × multiplier
A8: Simulated total revenue (at ORIGINAL prices) | B8: ='Source Data'!D12*B4 -> 1085 | C8: Volume scales; price list unchanged
A9: Simulated avg daily revenue | B9: =B8/7 -> 155
A10: Average NEW price after discount | B10: ='Source Data'!E12 -> 26.875 | C10: Live from Source Data (already uses Discount)
A11: # Styles under $30 after discount | B11: ='Source Data'!F12 -> 4 | C11: Live count
A12: Projected 4-week revenue @ original prices | B12: =B8*4 -> 4340
A13: Projected 4-week revenue @ new prices (same volume) | B13: ='Source Data'!G12*B4*4 -> 3660
A14: Cost of the discount (4 weeks, same volume) | B14: =B12-B13 -> 680
A16: SENSITIVITY TABLE — Effect of different discount amounts (volume held at last-week levels)
A17: Discount ($) | B17: Avg New Price | C17: # Under $30 | D17: 4-wk Rev @ New Prices | E17: Cost of Discount (4 wk)
A18: 0 | B18: ='Source Data'!B12-0 -> 31.875 | C18: =SUMPRODUCT(--(('Source Data'!B4:B11-0)<30)) -> 3 | D18: =4*SUMPRODUCT(('Source Data'!B4:B11-0)*'Source Data'!C4:C11) -> 4340 | E18: =4*'Source Data'!D12-D18 -> 0
A19: 3 | B19: ='Source Data'!B12-3 -> 28.875 | C19: =SUMPRODUCT(--(('Source Data'!B4:B11-3)<30)) -> 4 | D19: =4*SUMPRODUCT(('Source Data'!B4:B11-3)*'Source Data'!C4:C11) -> 3932 | E19: =4*'Source Data'!D12-D19 -> 408
A20: 5 | B20: ='Source Data'!B12-5 -> 26.875 | C20: =SUMPRODUCT(--(('Source Data'!B4:B11-5)<30)) -> 4 | D20: =4*SUMPRODUCT(('Source Data'!B4:B11-5)*'Source Data'!C4:C11) -> 3660 | E20: =4*'Source Data'!D12-D20 -> 680
A21: 8 | B21: ='Source Data'!B12-8 -> 23.875 | C21: =SUMPRODUCT(--(('Source Data'!B4:B11-8)<30)) -> 6 | D21: =4*SUMPRODUCT(('Source Data'!B4:B11-8)*'Source Data'!C4:C11) -> 3252 | E21: =4*'Source Data'!D12-D21 -> 1088
A22: 10 | B22: ='Source Data'!B12-10 -> 21.875 | C22: =SUMPRODUCT(--(('Source Data'!B4:B11-10)<30)) -> 6 | D22: =4*SUMPRODUCT(('Source Data'!B4:B11-10)*'Source Data'!C4:C11) -> 2980 | E22: =4*'Source Data'!D12-D22 -> 1360
A24: Tip: The green row is the current default ($5). Change B3 above and the live metrics update; this table always shows the full range for comparison.
A26: PRACTICE IDEA
A27: Try Discount = 3 and Multiplier = 1.2. Does the number of under-$30 styles increase enough, and does the extra volume offset the smaller per-cut discount? Discuss with Carly which combination fits her brand.

Sheet Charts Data
A1: Helper data for charts (linked to Source Data so charts stay live)
A3: Style | B3: Original Price | C3: New Price | D3: Units Sold | E3: Revenue (original)
A4: ='Source Data'!A4 -> bouffant | B4: ='Source Data'!B4 -> 30 | C4: ='Source Data'!E4 -> 25 | D4: ='Source Data'!C4 -> 2 | E4: ='Source Data'!D4 -> 60
A5: ='Source Data'!A5 -> pixie | B5: ='Source Data'!B5 -> 25 | C5: ='Source Data'!E5 -> 20 | D5: ='Source Data'!C5 -> 3 | E5: ='Source Data'!D5 -> 75
A6: ='Source Data'!A6 -> dreadlocks | B6: ='Source Data'!B6 -> 40 | C6: ='Source Data'!E6 -> 35 | D6: ='Source Data'!C6 -> 5 | E6: ='Source Data'!D6 -> 200
A7: ='Source Data'!A7 -> crew | B7: ='Source Data'!B7 -> 20 | C7: ='Source Data'!E7 -> 15 | D7: ='Source Data'!C7 -> 8 | E7: ='Source Data'!D7 -> 160
A8: ='Source Data'!A8 -> bowl | B8: ='Source Data'!B8 -> 20 | C8: ='Source Data'!E8 -> 15 | D8: ='Source Data'!C8 -> 4 | E8: ='Source Data'!D8 -> 80
A9: ='Source Data'!A9 -> bob | B9: ='Source Data'!B9 -> 35 | C9: ='Source Data'!E9 -> 30 | D9: ='Source Data'!C9 -> 4 | E9: ='Source Data'!D9 -> 140
A10: ='Source Data'!A10 -> mohawk | B10: ='Source Data'!B10 -> 50 | C10: ='Source Data'!E10 -> 45 | D10: ='Source Data'!C10 -> 6 | E10: ='Source Data'!D10 -> 300
A11: ='Source Data'!A11 -> flattop | B11: ='Source Data'!B11 -> 35 | C11: ='Source Data'!E11 -> 30 | D11: ='Source Data'!C11 -> 2 | E11: ='Source Data'!D11 -> 70

Sheet Notes & GS Guide
A1: Data Dictionary, Method Notes & Google Sheets Compatibility
A3: Data Dictionary
A4: Style | B4: Name of the haircut offered at Carly’s Clippers
A5: Original Price ($) | B5: List price before any promotional discount (editable yellow cells)
A6: Units Last Week | B6: Number of times that style was purchased in the past 7 days (editable)
A7: Revenue ($) | B7: Original Price × Units (formula)
A8: New Price ($) | B8: Original Price − Discount (Discount lives on Simulator!B3)
A9: Under $30? | B9: Yes if New Price < 30; used for the advertising list
A10: Revenue @ New Price | B10: What revenue would have been if the discounted price had been charged last week
A12: Why a spreadsheet version?
A13: The Python notebooks are ideal for learning loops, list comprehensions and reproducible analysis. This workbook shows the same business questions answered with spreadsheet strengths: • Instant what-if (edit Discount or a single price → everything updates) • Conditional formatting that flags under-$30 styles automatically • Charts that non-technical stakeholders (Carly) can open on a phone • No need to re-execute code; formulas are the source of truth • Easy collaboration via Google Sheets sharing links
A19: Google Sheets import instructions
A20: 1. In Google Drive click New → File upload → select this .xlsx 2. Open the uploaded file with Google Sheets 3. (Optional) File → Save as Google Sheets for full native editing 4. Yellow input cells remain editable; charts may need a slight resize 5. All SUM / AVERAGE / IF / SUMPRODUCT / INDEX-MATCH formulas used here are fully supported in Sheets
A26: Relationship to the Jupyter notebooks
A27: Practice Skeleton & Solution notebooks contain the Python loops, list comprehensions, alternate zip/dict solutions, matplotlib charts and the interactive simulation cell. Use the notebooks to learn the programming patterns; use this workbook to explore the business numbers with Carly or other non-coding stakeholders and to perform rapid what-if analysis.
